aspose/__init__.py
aspose/email.cpython-310-x86_64-linux-gnu.so
aspose/email.cpython-311-x86_64-linux-gnu.so
aspose/email.cpython-312-x86_64-linux-gnu.so
aspose/email.cpython-313-x86_64-linux-gnu.so
aspose/email.cpython-35m-x86_64-linux-gnu.so
aspose/email.cpython-36m-x86_64-linux-gnu.so
aspose/email.cpython-37m-x86_64-linux-gnu.so
aspose/email.cpython-38-x86_64-linux-gnu.so
aspose/email.cpython-39-x86_64-linux-gnu.so
aspose/pycore.cpython-310-x86_64-linux-gnu.so
aspose/pycore.cpython-311-x86_64-linux-gnu.so
aspose/pycore.cpython-312-x86_64-linux-gnu.so
aspose/pycore.cpython-313-x86_64-linux-gnu.so
aspose/pycore.cpython-35m-x86_64-linux-gnu.so
aspose/pycore.cpython-36m-x86_64-linux-gnu.so
aspose/pycore.cpython-37m-x86_64-linux-gnu.so
aspose/pycore.cpython-38-x86_64-linux-gnu.so
aspose/pycore.cpython-39-x86_64-linux-gnu.so
aspose/pygc.cpython-310-x86_64-linux-gnu.so
aspose/pygc.cpython-311-x86_64-linux-gnu.so
aspose/pygc.cpython-312-x86_64-linux-gnu.so
aspose/pygc.cpython-313-x86_64-linux-gnu.so
aspose/pygc.cpython-35m-x86_64-linux-gnu.so
aspose/pygc.cpython-36m-x86_64-linux-gnu.so
aspose/pygc.cpython-37m-x86_64-linux-gnu.so
aspose/pygc.cpython-38-x86_64-linux-gnu.so
aspose/pygc.cpython-39-x86_64-linux-gnu.so
aspose/pyreflection.cpython-310-x86_64-linux-gnu.so
aspose/pyreflection.cpython-311-x86_64-linux-gnu.so
aspose/pyreflection.cpython-312-x86_64-linux-gnu.so
aspose/pyreflection.cpython-313-x86_64-linux-gnu.so
aspose/pyreflection.cpython-35m-x86_64-linux-gnu.so
aspose/pyreflection.cpython-36m-x86_64-linux-gnu.so
aspose/pyreflection.cpython-37m-x86_64-linux-gnu.so
aspose/pyreflection.cpython-38-x86_64-linux-gnu.so
aspose/pyreflection.cpython-39-x86_64-linux-gnu.so
aspose/__pyinstaller/__init__.pyi
aspose/__pyinstaller/hook-aspose.py
aspose/assemblies/email/Aspose.Email.dll
aspose/assemblies/email/System.Formats.Asn1.dll
aspose/assemblies/email/System.Runtime.CompilerServices.Unsafe.dll
aspose/assemblies/email/System.Security.Cryptography.Cng.dll
aspose_email_for_python_via_net-25.12.dist-info/METADATA
aspose_email_for_python_via_net-25.12.dist-info/WHEEL
aspose_email_for_python_via_net-25.12.dist-info/entry_points.txt
aspose_email_for_python_via_net-25.12.dist-info/top_level.txt
aspose_email_for_python_via_net-25.12.dist-info/RECORD
