Metadata-Version: 2.1
Name: Aspose.Email-for-Python-via-NET
Version: 25.12
Summary: A collection of components for working with email. It makes it easy to work with Outlook PST, EML, MSG and MHT files.
Home-page: https://products.aspose.com/email/python-net
Author: Aspose
License: https://company.aspose.com/legal/eula
Keywords: Email,eml,msg,pst,ost,outlook,exchange,imap,smtp,pop3,thef,mht,mbo
Platform: linux_x86_64
Classifier: Operating System :: Microsoft :: Windows
Classifier: License :: Other/Proprietary License
Classifier: Programming Language :: Python :: 3
Classifier: Programming Language :: Python :: 3 :: Only
Classifier: Programming Language :: Python :: 3.8
Classifier: Programming Language :: Python :: 3.9
Classifier: Programming Language :: Python :: 3.10
Classifier: Programming Language :: Python :: 3.11
Classifier: Programming Language :: Python :: 3.12
Classifier: Programming Language :: Python :: 3.13
Classifier: Topic :: Software Development :: Libraries
Classifier: Topic :: Communications
Classifier: Topic :: Communications :: Email
Requires-Python: >=3.5,<3.14
